simple_tsv/__init__.py
simple_tsv-1.0.1.dist-info/LICENSE.txt
simple_tsv-1.0.1.dist-info/METADATA
simple_tsv-1.0.1.dist-info/WHEEL
simple_tsv-1.0.1.dist-info/top_level.txt
simple_tsv-1.0.1.dist-info/RECORD
