Metadata-Version: 2.1
Name: simple-tsv
Version: 1.0.1
Summary: basic tsv handling
Author-email: Johannes Programming <johannes-programming@posteo.org>
License: The MIT License (MIT)
Project-URL: Download, https://pypi.org/project/simple-tsv/#files
Project-URL: Source, https://github.com/johannes-programming/simple_tsv
Classifier: License :: OSI Approved :: MIT License
Classifier: Programming Language :: Python
Classifier: Programming Language :: Python :: 3
Requires-Python: >=3.11
License-File: LICENSE.txt
Requires-Dist: pandas >=2.1.2
